Level_Up_RPG/__init__.py
Level_Up_RPG/level_up_rpg.py
Level_Up_RPG-1.dist-info/LICENSE
Level_Up_RPG-1.dist-info/METADATA
Level_Up_RPG-1.dist-info/WHEEL
Level_Up_RPG-1.dist-info/entry_points.txt
Level_Up_RPG-1.dist-info/top_level.txt
Level_Up_RPG-1.dist-info/RECORD
