Metadata-Version: 2.1
Name: Level-Up-RPG
Version: 1
Summary: This package contains implementation of the game "Level_Up_RPG".
Home-page: https://github.com/DtjiAppDev/LEVEL_UP_RPG
Author: Dtji AppDev
Author-email: dtjiappdev1999@gmail.com
License: MIT
Platform: UNKNOWN
Classifier: Programming Language :: Python :: 3
Classifier: Programming Language :: Python :: 3.7
